simple_openai_requests/__init__.py
simple_openai_requests/batch_requests.py
simple_openai_requests/caching.py
simple_openai_requests/db_caching.py
simple_openai_requests/simple_openai_requests.py
simple_openai_requests/synchronous_requests.py
simple_openai_requests-1.1.0.dist-info/METADATA
simple_openai_requests-1.1.0.dist-info/WHEEL
simple_openai_requests-1.1.0.dist-info/top_level.txt
simple_openai_requests-1.1.0.dist-info/RECORD
