Metadata-Version: 2.1
Name: simple_openai_requests
Version: 1.1.0
Summary: Unify common OpenAI API requests use cases into a simple interface
Home-page: https://github.com/lehoanganh298/simple_openai_requests
Author: Le Hoang Anh
Author-email: lehoanganh29896@gmail.com
Classifier: Development Status :: 3 - Alpha
Classifier: Intended Audience :: Developers
Classifier: License :: OSI Approved :: MIT License
Classifier: Operating System :: OS Independent
Classifier: Programming Language :: Python :: 3
Classifier: Programming Language :: Python :: 3.7
Classifier: Programming Language :: Python :: 3.8
Classifier: Programming Language :: Python :: 3.9
Classifier: Programming Language :: Python :: 3.10
Requires-Python: >=3.7
Requires-Dist: openai >=1.0.0
Requires-Dist: tqdm >=4.0.0
